bioprocs/__init__.py
bioprocs/algorithm.py
bioprocs/bcftools.py
bioprocs/bed.py
bioprocs/bedtools.py
bioprocs/bwtool.py
bioprocs/chipseq.py
bioprocs/cluster.py
bioprocs/cnvkit.py
bioprocs/common.py
bioprocs/console/__init__.py
bioprocs/console/arguments.py
bioprocs/console/pipeline/__init__.py
bioprocs/console/pipeline/bioprocs_deg.py
bioprocs/console/pipeline/bioprocs_gplot.py
bioprocs/console/pipeline/bioprocs_mutcall.py
bioprocs/console/pipeline/bioprocs_pwmscan.py
bioprocs/console/pipeline/bioprocs_runcmds.py
bioprocs/console/utils.py
bioprocs/docx.py
bioprocs/eqtl.py
bioprocs/fastx.py
bioprocs/gatk.py
bioprocs/gene.py
bioprocs/genomeplot.py
bioprocs/gsea.py
bioprocs/hic.py
bioprocs/imtherapy.py
bioprocs/marray.py
bioprocs/misc.py
bioprocs/mlearn.py
bioprocs/network.py
bioprocs/picard.py
bioprocs/plink.py
bioprocs/plot.py
bioprocs/power.py
bioprocs/rank.py
bioprocs/reports/bcftools/pFilter.md
bioprocs/reports/bcftools/pStats.md
bioprocs/reports/gsea/pEnrichr.md
bioprocs/reports/imtherapy/pTopiary.md
bioprocs/reports/mlearn/pCrossValid.md
bioprocs/reports/mlearn/pGlmTest.md
bioprocs/reports/mlearn/pGlmTrain.md
bioprocs/reports/plot/pROC.md
bioprocs/reports/rnaseq/pRNASeqDEG.md
bioprocs/reports/stats/pCorr.md
bioprocs/reports/stats/pPCA.md
bioprocs/reports/stats/pStats.md
bioprocs/reports/stats/pSurvival.md
bioprocs/reports/tcgamaf/pDToxoG.md
bioprocs/reports/tcgamaf/pMaftools.md
bioprocs/reports/tumhet/pClonEvol.md
bioprocs/reports/tumhet/pLichee.md
bioprocs/reports/tumhet/pPyClone.md
bioprocs/reports/tumhet/pSchism.md
bioprocs/resource.py
bioprocs/rnaseq.py
bioprocs/sambam.py
bioprocs/scripts/__init__.py
bioprocs/scripts/algorithm/pAR.r
bioprocs/scripts/algorithm/pColoc.r
bioprocs/scripts/algorithm/pRWR.r
bioprocs/scripts/bcftools/pAnnotate.py
bioprocs/scripts/bcftools/pFilter.py
bioprocs/scripts/bcftools/pQuery.py
bioprocs/scripts/bcftools/pReheader.py
bioprocs/scripts/bcftools/pView.py
bioprocs/scripts/bed/pBedLiftover.py
bioprocs/scripts/bed/pBedSort.py
bioprocs-0.1.2.dist-info/entry_points.txt
bioprocs-0.1.2.dist-info/LICENSE
bioprocs-0.1.2.dist-info/WHEEL
bioprocs-0.1.2.dist-info/METADATA
bioprocs-0.1.2.dist-info/RECORD
