Metadata-Version: 2.1
Name: bioprocs
Version: 0.1.2
Summary: A set of PyPPL processes for bioinformatics.
License: MIT
Author: pwwang
Author-email: pwwang@pwwang.com
Requires-Python: >=3.6,<4.0
Classifier: License :: OSI Approved :: MIT License
Classifier: Programming Language :: Python :: 3
Classifier: Programming Language :: Python :: 3.6
Classifier: Programming Language :: Python :: 3.7
Requires-Dist: PyPPL
Requires-Dist: completions
Requires-Dist: pyparam
Requires-Dist: python-box87
